ina219.py
pi_ina219-1.3.0.dist-info/LICENSE.md
pi_ina219-1.3.0.dist-info/METADATA
pi_ina219-1.3.0.dist-info/WHEEL
pi_ina219-1.3.0.dist-info/top_level.txt
pi_ina219-1.3.0.dist-info/RECORD
